{
    "1": {
        "name": "cnn",
        "file": "cnn.cpp",
        "fileloc": "300",
        "instructions": "150",
        "total_instructions": "15412",
        "calls": "3 4 6 2 5",
        "basicblocks": "10",
        "loads": {
            "L": "26"
        },
        "stores": {
            "L": "2"
        },
        "loops": {
            "L": "1",
            "N": "2"
        }
    },
    "2": {
        "name": "cnn_Pipeline_VITIS_LOOP_329_4",
        "file": "cnn.cpp",
        "fileloc": "329",
        "instructions": "14806",
        "total_instructions": "14806",
        "calls": "",
        "basicblocks": "4",
        "loads": {
            "L": "1366"
        },
        "stores": {
            "L": "228"
        },
        "loops": {
            "L": "1"
        }
    },
    "3": {
        "name": "load_weight_S0",
        "file": "cnn.cpp",
        "fileloc": "173",
        "instructions": "14",
        "total_instructions": "101",
        "calls": "10",
        "basicblocks": "1"
    },
    "0": {
        "name": "kernel_cnn",
        "file": "cnn.cpp",
        "fileloc": "386",
        "instructions": "41",
        "total_instructions": "15453",
        "calls": "1",
        "basicblocks": "1"
    },
    "4": {
        "name": "load_output_S0",
        "file": "cnn.cpp",
        "fileloc": "106",
        "instructions": "14",
        "total_instructions": "148",
        "calls": "7",
        "basicblocks": "1"
    },
    "5": {
        "name": "store_output_S0",
        "file": "cnn.cpp",
        "fileloc": "229",
        "instructions": "15",
        "total_instructions": "134",
        "calls": "8",
        "basicblocks": "1"
    },
    "6": {
        "name": "load_input_S0",
        "file": "cnn.cpp",
        "fileloc": "48",
        "instructions": "14",
        "total_instructions": "73",
        "calls": "9",
        "basicblocks": "1"
    },
    "7": {
        "name": "load_output_S0_Pipeline_VITIS_LOOP_117_1_VITIS_LOOP_118_2_VITIS_LOOP_119_3",
        "file": "cnn.cpp",
        "fileloc": "117",
        "instructions": "134",
        "total_instructions": "134",
        "calls": "",
        "basicblocks": "4",
        "loads": {
            "L": "6"
        },
        "stores": {
            "L": "28"
        },
        "loops": {
            "L": "1"
        }
    },
    "8": {
        "name": "store_output_S0_Pipeline_VITIS_LOOP_240_1_VITIS_LOOP_241_2_VITIS_LOOP_242_3",
        "file": "cnn.cpp",
        "fileloc": "240",
        "instructions": "119",
        "total_instructions": "119",
        "calls": "",
        "basicblocks": "4",
        "loads": {
            "L": "22"
        },
        "stores": {
            "L": "12"
        },
        "loops": {
            "L": "1"
        }
    },
    "9": {
        "name": "load_input_S0_Pipeline_VITIS_LOOP_63_2_VITIS_LOOP_64_3",
        "file": "cnn.cpp",
        "fileloc": "63",
        "instructions": "59",
        "total_instructions": "59",
        "calls": "",
        "basicblocks": "4",
        "loads": {
            "L": "4"
        },
        "stores": {
            "L": "12"
        },
        "loops": {
            "L": "1"
        }
    },
    "10": {
        "name": "load_weight_S0_Pipeline_VITIS_LOOP_186_1_VITIS_LOOP_187_2_VITIS_LOOP_188_3_VITIS",
        "file": "cnn.cpp",
        "fileloc": "186",
        "instructions": "87",
        "total_instructions": "87",
        "calls": "",
        "basicblocks": "4",
        "loads": {
            "L": "7"
        },
        "stores": {
            "L": "15"
        },
        "loops": {
            "L": "1"
        }
    }
}
